README
setup.py
pyspotify_helper/__init__.py
pyspotify_helper/spotify_utils.py
pyspotify_helper.egg-info/PKG-INFO
pyspotify_helper.egg-info/SOURCES.txt
pyspotify_helper.egg-info/dependency_links.txt
pyspotify_helper.egg-info/requires.txt
pyspotify_helper.egg-info/top_level.txt