Metadata-Version: 1.0
Name: pyspotify-helper
Version: 0.0.1
Summary: Simplest integration of Spotify into Python
Home-page: https://github.com/MattWis/pyspotify_helper.git
Author: Matt Wismer
Author-email: mattwis86@gmail.com
License: MIT
Platform: UNKNOWN
